libtoolbox/__init__.py
libtoolbox/path.py
libtoolbox-0.1.0.dist-info/WHEEL
libtoolbox-0.1.0.dist-info/METADATA
libtoolbox-0.1.0.dist-info/RECORD
